custom_json_encoder/__init__.py
custom_json_encoder/__main__.py
tests/__init__.py
tests/test_encoder.py
custom_json_encoder-0.5.0.dist-info/LICENSE
custom_json_encoder-0.5.0.dist-info/METADATA
custom_json_encoder-0.5.0.dist-info/WHEEL
custom_json_encoder-0.5.0.dist-info/entry_points.txt
custom_json_encoder-0.5.0.dist-info/top_level.txt
custom_json_encoder-0.5.0.dist-info/RECORD
