Metadata-Version: 2.1
Name: custom-json-encoder
Version: 0.5.0
Summary: A JSON encoder that allows customizing the indentation based on the content and
Home-page: https://github.com/Kerrigan29a/py_custom_json_encoder
Author: Javier Escalada Gómez
Author-email: kerrigan29a@gmail.com
License: BSD 3-Clause Clear License
Project-URL: Source, https://github.com/Kerrigan29a/py_custom_json_encoder
Keywords: json,encoder,pretty-print,width
Platform: any
Classifier: Development Status :: 4 - Beta
Classifier: Environment :: Console
Classifier: Intended Audience :: End Users/Desktop
Classifier: Intended Audience :: Developers
Classifier: License :: OSI Approved :: BSD License
Classifier: Operating System :: OS Independent
Classifier: Programming Language :: Python :: 3 :: Only
Classifier: Topic :: Utilities
License-File: LICENSE
